{
    "pesticide": {
        "PPE": "Applicators and other handlers must wear: long-sleeved shirt and long pants; shoes plus socks. In addition, mixers, loaders, and applicators using mechanically pressurized handwands must wear a NIOSH-approved particulate filtering facepiece respirator with any R or P filter, or a NIOSH-approved elastomeric particulate respirator with any R or P filter, or a NIOSH-approved powered air-purifying respirator with HE filters. Follow manufacturer\u2019s instructions for cleaning/maintaining PPE. If no such instructions for washables exist, use detergent and hot water. Keep and wash PPE separately from other laundry.",
        "PPE_page": 2,
        "signal_word": "CAUTION",
        "label_url": "",
        "epa_reg_no": "1381-275",
        "trade_Name": "Altipro\u2122 F",
        "Active_Ingredients": [
            {
                "name": "Prothioconazole",
                "mode_Of_Action": "Group 3 fungicide"
            },
            {
                "name": "Azoxystrobin",
                "mode_Of_Action": "Group 11 fungicide"
            }
        ],
        "Safety_Information": {
            "general_Info": "CAUTION: Harmful if swallowed. Wash thoroughly with soap and water after handling and before eating, drinking, chewing gum, using tobacco, or using the toilet.",
            "if_In_Eyes": "N/A",
            "if_Swallowed": "Call a poison control center or doctor immediately for treatment advice. Have person sip a glass of water if able to swallow. DO NOT induce vomiting unless told to do so by a poison control center or doctor. DO NOT give anything by mouth to an unconscious person.",
            "if_Inhaled": "N/A",
            "if_On_Skin": "N/A",
            "physician_Note": "No specific antidote. Treat Symptomatically.",
            "page": 1
        },
        "Application_Info": [
            {
                "low_rate": 4.0,
                "low_rate_page": 6,
                "high_rate": 6.0,
                "units": "fl. oz.",
                "max_product_per_acre_per_season": "DO NOT exceed 0.713 lb. a.i. prothioconazole per acre per year or 2.0 lbs. a.i. azoxystrobin per acre per year",
                "max_product_per_acre_per_season_page": 6,
                "max_applications_per_season": "DO NOT exceed 5 applications per year of this product at the high rate (12.0 fl. oz.)",
                "REI": "12 hours",
                "REI_page": 6,
                "PHI": "Forage: 7 days; Grain and Fodder: 14 days",
                "PHI_page": 6,
                "application_Method": "Ground; Aerial",
                "Target_Crop": [
                    {
                        "name": "corn",
                        "page": 6
                    }
                ],
                "Target_Disease_Pest": [
                    {
                        "name": "Anthracnose Leaf Blight",
                        "page": 6
                    },
                    {
                        "name": "Eyespot",
                        "page": 6
                    },
                    {
                        "name": "Gray Leaf Spot",
                        "page": 6
                    }
                ]
            },
            {
                "low_rate": 8.0,
                "low_rate_page": 6,
                "high_rate": 12.0,
                "units": "fl. oz.",
                "max_product_per_acre_per_season": "DO NOT exceed 0.713 lb. a.i. prothioconazole per acre per year or 2.0 lbs. a.i. azoxystrobin per acre per year",
                "max_product_per_acre_per_season_page": 6,
                "max_applications_per_season": "DO NOT exceed 5 applications per year of this product at the high rate (12.0 fl. oz.)",
                "REI": "12 hours",
                "REI_page": 6,
                "PHI": "Forage: 7 days; Grain and Fodder: 14 days",
                "PHI_page": 6,
                "application_Method": "Ground; Aerial",
                "Target_Crop": [
                    {
                        "name": "corn",
                        "page": 6
                    }
                ],
                "Target_Disease_Pest": [
                    {
                        "name": "Anthracnose Leaf Blight",
                        "page": 6
                    },
                    {
                        "name": "Eyespot",
                        "page": 6
                    },
                    {
                        "name": "Gray Leaf Spot",
                        "page": 6
                    },
                    {
                        "name": "Northern Corn Leaf Blight",
                        "page": 6
                    },
                    {
                        "name": "Northern Corn Leaf Spot",
                        "page": 6
                    },
                    {
                        "name": "Rust",
                        "page": 6
                    },
                    {
                        "name": "Physoderma Brown Spot",
                        "page": 6
                    },
                    {
                        "name": "Southern Corn Leaf Blight",
                        "page": 6
                    },
                    {
                        "name": "Tar spot",
                        "page": 6
                    }
                ]
            },
            {
                "low_rate": 8.0,
                "low_rate_page": 7,
                "high_rate": 8.0,
                "units": "fl. oz.",
                "max_product_per_acre_per_season": "DO NOT exceed 0.713 lb. a.i. prothioconazole per acre per year or 2.0 lbs. a.i. azoxystrobin per acre per year",
                "max_product_per_acre_per_season_page": 7,
                "max_applications_per_season": "DO NOT exceed 7 applications of this product per year.",
                "REI": "24 hours",
                "REI_page": 7,
                "PHI": "Forage and ears: 7 days; Fodder: 14 days",
                "PHI_page": 7,
                "application_Method": "Ground; Aerial",
                "Target_Crop": [
                    {
                        "name": "corn",
                        "page": 7
                    }
                ],
                "Target_Disease_Pest": [
                    {
                        "name": "Anthracnose Leaf Blight",
                        "page": 7
                    },
                    {
                        "name": "Eye Spot",
                        "page": 7
                    },
                    {
                        "name": "Gray Leaf Spot",
                        "page": 7
                    },
                    {
                        "name": "Northern Corn Leaf Blight",
                        "page": 7
                    },
                    {
                        "name": "Northern Corn Leaf Spot",
                        "page": 7
                    },
                    {
                        "name": "Rusts",
                        "page": 7
                    },
                    {
                        "name": "Southern Corn Leaf Blight",
                        "page": 7
                    },
                    {
                        "name": "Tar spot",
                        "page": 7
                    }
                ]
            },
            {
                "low_rate": 12.0,
                "low_rate_page": 8,
                "high_rate": 12.0,
                "units": "fl. oz.",
                "max_product_per_acre_per_season": "DO NOT exceed 0.534 lb. a.i. prothioconazole per acre per year or 1.5 lbs. a.i. azoxystrobin per acre per year",
                "max_product_per_acre_per_season_page": 8,
                "max_applications_per_season": "DO NOT exceed 3 applications of this product per year.",
                "REI": "12 hours",
                "REI_page": 8,
                "PHI": "14 days; If growing for animal feed, DO NOT apply within 7 days of cutting or swathing of the crop for forage.",
                "PHI_page": 8,
                "application_Method": "Ground; Aerial",
                "Target_Crop": [
                    {
                        "name": "dry beans",
                        "page": 8
                    }
                ],
                "Target_Disease_Pest": [
                    {
                        "name": "Anthracnose",
                        "page": 8
                    },
                    {
                        "name": "Ascochyta blight",
                        "page": 8
                    },
                    {
                        "name": "Ascochyta leaf and pod spot",
                        "page": 8
                    },
                    {
                        "name": "Grey Mold",
                        "page": 8
                    },
                    {
                        "name": "Mycosphaerella blight",
                        "page": 8
                    },
                    {
                        "name": "White mold",
                        "page": 8
                    }
                ]
            },
            {
                "low_rate": 8.0,
                "low_rate_page": 10,
                "high_rate": 11.0,
                "units": "fl. oz.",
                "max_product_per_acre_per_season": "DO NOT exceed 0.53 lb. a.i. prothioconazole per acre per year or 1.5 lbs. a.i. azoxystrobin per acre per year",
                "max_product_per_acre_per_season_page": 10,
                "max_applications_per_season": "DO NOT exceed 4 foliar applications of this product at the maximum application rate (11.0 fl. oz.)",
                "REI": "12 hours",
                "REI_page": 10,
                "PHI": "21 days",
                "PHI_page": 10,
                "application_Method": "Ground; Aerial",
                "Target_Crop": [
                    {
                        "name": "soybeans",
                        "page": 10
                    }
                ],
                "Target_Disease_Pest": [
                    {
                        "name": "Alternaria Leaf Spot",
                        "page": 10
                    },
                    {
                        "name": "Anthracnose",
                        "page": 10
                    },
                    {
                        "name": "Asian Soybean Rust",
                        "page": 10
                    },
                    {
                        "name": "Brown Spot",
                        "page": 10
                    },
                    {
                        "name": "Cercospora Blight",
                        "page": 10
                    },
                    {
                        "name": "Frogeye Leaf Spot",
                        "page": 10
                    },
                    {
                        "name": "Pod & Stem Blight",
                        "page": 10
                    },
                    {
                        "name": "Powdery Mildew",
                        "page": 10
                    },
                    {
                        "name": "Rhizoctonia Aerial Blight",
                        "page": 10
                    },
                    {
                        "name": "Sclerotinia Stem Rot",
                        "page": 10
                    }
                ]
            },
            {
                "low_rate": 8.0,
                "low_rate_page": 11,
                "high_rate": 8.0,
                "units": "fl. oz.",
                "max_product_per_acre_per_season": "DO NOT exceed 0.293 lb. a.i. prothioconazole per acre per year or 0.40 lb. a.i. azoxystrobin per acre per year",
                "max_product_per_acre_per_season_page": 11,
                "max_applications_per_season": "DO NOT exceed 2 applications of this product per year.",
                "REI": "12 hours",
                "REI_page": 11,
                "PHI": "30 days",
                "PHI_page": 11,
                "application_Method": "Ground; Aerial",
                "Target_Crop": [
                    {
                        "name": "wheat",
                        "page": 11
                    }
                ],
                "Target_Disease_Pest": [
                    {
                        "name": "Powdery Mildew",
                        "page": 11
                    },
                    {
                        "name": "Rusts",
                        "page": 11
                    },
                    {
                        "name": "Septoria Blotch",
                        "page": 11
                    },
                    {
                        "name": "Stagonospora Blotch",
                        "page": 11
                    },
                    {
                        "name": "Tan Spot",
                        "page": 11
                    }
                ]
            }
        ]
    }
}