{
    "pesticide": {
        "PPE": "Long-sleeved shirt and long pants; shoes plus socks",
        "PPE_page": 2,
        "signal_word": "CAUTION",
        "label_url": "",
        "epa_reg_no": "7969-311-1381",
        "trade_Name": "Everlon",
        "Active_Ingredients": [
            {
                "name": "fluxapyroxad",
                "mode_Of_Action": "Group 7 fungicide"
            },
            {
                "name": "pyraclostrobin",
                "mode_Of_Action": "Group 11 fungicide"
            }
        ],
        "Safety_Information": {
            "general_Info": "CAUTION. Harmful if swallowed. Avoid contact with skin or clothing.",
            "if_In_Eyes": "N/A",
            "if_Swallowed": "Call a poison control center or doctor immediately for treatment advice. Have person sip a glass of water if able to swallow. DO NOT induce vomiting unless told to do so by a poison control center or doctor. DO NOT give anything to an unconscious person.",
            "if_On_Skin": "N/A",
            "if_Inhaled": "N/A",
            "physician_Note": "Have the product container or label with you when calling a poison control center or doctor or going for treatment.",
            "page": 1
        },
        "Application_Info": [
            {
                "low_rate": 4,
                "low_rate_page": 11,
                "high_rate": 6.9,
                "units": "fl ozs/A",
                "max_product_per_acre_per_season": "20.7 fl ozs/A",
                "max_product_per_acre_per_season_page": 11,
                "max_applications_per_season": "3",
                "REI": "12 hours",
                "REI_page": 3,
                "PHI": "14 days",
                "PHI_page": 11,
                "application_Method": "Foliar",
                "Target_Crop": [
                    {
                        "name": "alfalfa",
                        "page": 11
                    }
                ],
                "Target_Disease_Pest": [
                    {
                        "name": "Anthracnose",
                        "page": 11
                    },
                    {
                        "name": "Common leaf spot",
                        "page": 11
                    },
                    {
                        "name": "Downy mildew",
                        "page": 11
                    },
                    {
                        "name": "Leaf spot",
                        "page": 11
                    },
                    {
                        "name": "Powdery mildew",
                        "page": 11
                    },
                    {
                        "name": "Rhizoctonia blight/black patch",
                        "page": 11
                    },
                    {
                        "name": "Rust",
                        "page": 11
                    },
                    {
                        "name": "Spring black stem and leaf spot",
                        "page": 11
                    },
                    {
                        "name": "Stagonospora leaf spot",
                        "page": 11
                    },
                    {
                        "name": "Stemphyllium leaf spot",
                        "page": 11
                    },
                    {
                        "name": "Summer black stem and leaf spot",
                        "page": 11
                    },
                    {
                        "name": "Yellow leaf blotch",
                        "page": 11
                    }
                ]
            },
            {
                "low_rate": 6,
                "low_rate_page": 13,
                "high_rate": 8.2,
                "units": "fl ozs/A",
                "max_product_per_acre_per_season": "24.6 fl ozs/A",
                "max_product_per_acre_per_season_page": 13,
                "max_applications_per_season": "3",
                "REI": "12 hours",
                "REI_page": 3,
                "PHI": "3 days",
                "PHI_page": 13,
                "application_Method": "Foliar",
                "Target_Crop": [
                    {
                        "name": "cabbage",
                        "page": 13
                    }
                ],
                "Target_Disease_Pest": [
                    {
                        "name": "Alternaria leaf spot",
                        "page": 13
                    },
                    {
                        "name": "Anthracnose",
                        "page": 13
                    },
                    {
                        "name": "Black leg",
                        "page": 13
                    },
                    {
                        "name": "Cercospora leaf spot",
                        "page": 13
                    },
                    {
                        "name": "Powdery mildew",
                        "page": 13
                    },
                    {
                        "name": "Rhizoctonia blight",
                        "page": 13
                    },
                    {
                        "name": "Ring spot",
                        "page": 13
                    },
                    {
                        "name": "White leaf spot",
                        "page": 13
                    },
                    {
                        "name": "White rust",
                        "page": 13
                    },
                    {
                        "name": "Downy mildew",
                        "page": 13
                    }
                ]
            },
            {
                "low_rate": 4,
                "low_rate_page": 15,
                "high_rate": 8,
                "units": "fl ozs/A",
                "max_product_per_acre_per_season": "16 fl ozs/A",
                "max_product_per_acre_per_season_page": 15,
                "max_applications_per_season": "2",
                "REI": "12 hours",
                "REI_page": 3,
                "PHI": "21 days",
                "PHI_page": 15,
                "application_Method": "Foliar",
                "Target_Crop": [
                    {
                        "name": "corn",
                        "page": 15
                    }
                ],
                "Target_Disease_Pest": [
                    {
                        "name": "Anthracnose",
                        "page": 15
                    },
                    {
                        "name": "Eyespot",
                        "page": 15
                    },
                    {
                        "name": "Gray leaf spot",
                        "page": 15
                    },
                    {
                        "name": "Northern corn leaf blight",
                        "page": 15
                    },
                    {
                        "name": "Northern corn leaf spot",
                        "page": 15
                    },
                    {
                        "name": "Physoderma brown spot",
                        "page": 15
                    },
                    {
                        "name": "Rust, common",
                        "page": 15
                    },
                    {
                        "name": "Rust, southern",
                        "page": 15
                    },
                    {
                        "name": "Southern corn leaf blight",
                        "page": 15
                    },
                    {
                        "name": "Yellow leaf blight",
                        "page": 15
                    }
                ]
            },
            {
                "low_rate": 4,
                "low_rate_page": 17,
                "high_rate": 8,
                "units": "fl ozs/A",
                "max_product_per_acre_per_season": "16 fl ozs/A",
                "max_product_per_acre_per_season_page": 17,
                "max_applications_per_season": "2",
                "REI": "12 hours",
                "REI_page": 3,
                "PHI": "21 days",
                "PHI_page": 17,
                "application_Method": "Foliar",
                "Target_Crop": [
                    {
                        "name": "dry beans",
                        "page": 17
                    }
                ],
                "Target_Disease_Pest": [
                    {
                        "name": "Anthracnose",
                        "page": 17
                    },
                    {
                        "name": "Alternaria leaf and pod spot",
                        "page": 17
                    },
                    {
                        "name": "Ascochyta blight",
                        "page": 17
                    },
                    {
                        "name": "Asian soybean rust",
                        "page": 17
                    },
                    {
                        "name": "Botrytis gray mold",
                        "page": 17
                    },
                    {
                        "name": "Cercospora leaf spot",
                        "page": 17
                    },
                    {
                        "name": "Downy mildew",
                        "page": 17
                    },
                    {
                        "name": "Mycosphaerella blight",
                        "page": 17
                    },
                    {
                        "name": "Powdery mildew",
                        "page": 17
                    },
                    {
                        "name": "Rust",
                        "page": 17
                    },
                    {
                        "name": "White mold",
                        "page": 17
                    }
                ]
            },
            {
                "low_rate": 4,
                "low_rate_page": 18,
                "high_rate": 8,
                "units": "fl ozs/A",
                "max_product_per_acre_per_season": "16 fl ozs/A",
                "max_product_per_acre_per_season_page": 18,
                "max_applications_per_season": "2",
                "REI": "12 hours",
                "REI_page": 3,
                "PHI": "7 days",
                "PHI_page": 18,
                "application_Method": "Foliar",
                "Target_Crop": [
                    {
                        "name": "snap beans",
                        "page": 18
                    }
                ],
                "Target_Disease_Pest": [
                    {
                        "name": "Anthracnose",
                        "page": 18
                    },
                    {
                        "name": "Alternaria leaf and pod spot",
                        "page": 18
                    },
                    {
                        "name": "Ascochyta blight",
                        "page": 18
                    },
                    {
                        "name": "Asian soybean rust",
                        "page": 18
                    },
                    {
                        "name": "Botrytis gray mold",
                        "page": 18
                    },
                    {
                        "name": "Cercospora leaf spot",
                        "page": 18
                    },
                    {
                        "name": "Downy mildew",
                        "page": 18
                    },
                    {
                        "name": "Mycosphaerella blight",
                        "page": 18
                    },
                    {
                        "name": "Powdery mildew",
                        "page": 18
                    },
                    {
                        "name": "Rust",
                        "page": 18
                    },
                    {
                        "name": "White mold",
                        "page": 18
                    }
                ]
            },
            {
                "low_rate": 4,
                "low_rate_page": 19,
                "high_rate": 8,
                "units": "fl ozs/A",
                "max_product_per_acre_per_season": "24 fl ozs/A",
                "max_product_per_acre_per_season_page": 19,
                "max_applications_per_season": "3",
                "REI": "12 hours",
                "REI_page": 3,
                "PHI": "0 days",
                "PHI_page": 19,
                "application_Method": "Foliar",
                "Target_Crop": [
                    {
                        "name": "tomatoes",
                        "page": 19
                    }
                ],
                "Target_Disease_Pest": [
                    {
                        "name": "Anthracnose",
                        "page": 19
                    },
                    {
                        "name": "Black mold",
                        "page": 19
                    },
                    {
                        "name": "Early blight",
                        "page": 19
                    },
                    {
                        "name": "Septoria leaf spot",
                        "page": 19
                    },
                    {
                        "name": "Target spot",
                        "page": 19
                    },
                    {
                        "name": "Powdery mildew",
                        "page": 19
                    },
                    {
                        "name": "Botrytis gray mold",
                        "page": 19
                    },
                    {
                        "name": "Rhizoctonia stem rot",
                        "page": 19
                    },
                    {
                        "name": "Sclerotinia stem rot",
                        "page": 19
                    },
                    {
                        "name": "Southern blight",
                        "page": 19
                    },
                    {
                        "name": "Late blight",
                        "page": 19
                    }
                ]
            },
            {
                "low_rate": 4,
                "low_rate_page": 26,
                "high_rate": 8,
                "units": "fl ozs/A",
                "max_product_per_acre_per_season": "16 fl ozs/A",
                "max_product_per_acre_per_season_page": 26,
                "max_applications_per_season": "2",
                "REI": "12 hours",
                "REI_page": 3,
                "PHI": "21 days",
                "PHI_page": 26,
                "application_Method": "Foliar",
                "Target_Crop": [
                    {
                        "name": "soybeans",
                        "page": 26
                    }
                ],
                "Target_Disease_Pest": [
                    {
                        "name": "Alternaria leaf spot",
                        "page": 26
                    },
                    {
                        "name": "Anthracnose",
                        "page": 26
                    },
                    {
                        "name": "Asian soybean rust",
                        "page": 26
                    },
                    {
                        "name": "Brown spot",
                        "page": 26
                    },
                    {
                        "name": "Cercospora blight",
                        "page": 26
                    },
                    {
                        "name": "Frogeye leaf spot",
                        "page": 26
                    },
                    {
                        "name": "Pod and stem blight",
                        "page": 26
                    },
                    {
                        "name": "Rhizoctonia aerial blight",
                        "page": 26
                    },
                    {
                        "name": "Target Spot",
                        "page": 26
                    },
                    {
                        "name": "Sclerotinia blight",
                        "page": 26
                    },
                    {
                        "name": "Southern blight",
                        "page": 26
                    }
                ]
            },
            {
                "low_rate": 4,
                "low_rate_page": 30,
                "high_rate": 8,
                "units": "fl ozs/A",
                "max_product_per_acre_per_season": "24 fl ozs/A",
                "max_product_per_acre_per_season_page": 30,
                "max_applications_per_season": "3",
                "REI": "12 hours",
                "REI_page": 3,
                "PHI": "7 days",
                "PHI_page": 30,
                "application_Method": "Foliar",
                "Target_Crop": [
                    {
                        "name": "potatoes",
                        "page": 30
                    }
                ],
                "Target_Disease_Pest": [
                    {
                        "name": "Black dot",
                        "page": 30
                    },
                    {
                        "name": "Brown spot and Black pit",
                        "page": 30
                    },
                    {
                        "name": "Early blight",
                        "page": 30
                    },
                    {
                        "name": "Botrytis gray mold",
                        "page": 30
                    },
                    {
                        "name": "Late blight",
                        "page": 30
                    },
                    {
                        "name": "Leaf spot",
                        "page": 30
                    },
                    {
                        "name": "Powdery mildew",
                        "page": 30
                    },
                    {
                        "name": "Rust",
                        "page": 30
                    },
                    {
                        "name": "White mold",
                        "page": 30
                    }
                ]
            },
            {
                "low_rate": 4,
                "low_rate_page": 31,
                "high_rate": 8,
                "units": "fl ozs/A",
                "max_product_per_acre_per_season": "16 fl ozs/A",
                "max_product_per_acre_per_season_page": 31,
                "max_applications_per_season": "2",
                "REI": "12 hours",
                "REI_page": 3,
                "PHI": "21 days",
                "PHI_page": 31,
                "application_Method": "Foliar",
                "Target_Crop": [
                    {
                        "name": "wheat",
                        "page": 31
                    }
                ],
                "Target_Disease_Pest": [
                    {
                        "name": "Black point",
                        "page": 31
                    },
                    {
                        "name": "Leaf rust",
                        "page": 31
                    },
                    {
                        "name": "Powdery mildew",
                        "page": 31
                    },
                    {
                        "name": "Septoria leaf and glume blotch",
                        "page": 31
                    },
                    {
                        "name": "Spot blotch",
                        "page": 31
                    },
                    {
                        "name": "Stem rust",
                        "page": 31
                    },
                    {
                        "name": "Stripe rust",
                        "page": 31
                    },
                    {
                        "name": "Tan spot",
                        "page": 31
                    },
                    {
                        "name": "Eyespot",
                        "page": 31
                    }
                ]
            }
        ]
    }
}