{
    "pesticide": {
        "PPE": "Long-sleeved shirt and long pants; chemical resistant gloves (barrier laminate, butyl rubber \u226514 mils, nitrile rubber \u226514 mils, neoprene rubber \u226514 mils, polyvinyl chloride (PVC) \u226514 mils, Viton\u2122 \u226514 mils); shoes plus socks",
        "signal_word": "CAUTION",
        "label_url": "",
        "epa_reg_no": "100-1635",
        "trade_Name": "Vayantis\u00ae",
        "Active_Ingredients": [
            {
                "name": "Picarbutrazox",
                "mode_Of_Action": "Group U17 fungicide"
            }
        ],
        "Safety_Information": {
            "general_Info": "Harmful if swallowed or absorbed through skin. Causes moderate eye irritation. Avoid contact with skin, eyes or clothing. Wash thoroughly with soap and water after handling and before eating, drinking, chewing gum, using tobacco, or using the toilet. Remove and wash contaminated clothing before reuse.",
            "if_In_Eyes": "Hold eye open and rinse slowly and gently with water for 15-20 minutes. Remove contact lenses, if present, after the first 5 minutes, then continue rinsing. Call a poison control center or doctor for treatment advice.",
            "if_Swallowed": "Call a poison control center or doctor immediately for treatment advice. Have person sip a glass of water if able to swallow. Do not induce vomiting unless told to by a poison control center or doctor. Do not give anything by mouth to an unconscious person.",
            "if_On_Skin": "Take off contaminated clothing. Rinse skin immediately with plenty of water for 15-20 minutes. Call a poison control center or doctor for treatment advice.",
            "if_Inhaled": "N/A",
            "physician_Note": "Have the product container or label with you when calling a poison control center or doctor, or going for treatment."
        },
        "Application_Info": [
            {
                "low_rate": 0.039,
                "high_rate": 0.195,
                "units": "fl oz/100 lb seed",
                "max_product_per_acre_per_season": "0.0178 lb ai/A",
                "max_applications_per_season": "2 plantings per year",
                "REI": "4 hours",
                "PHI": "N/A",
                "application_Method": "Water-based slurry seed treatment",
                "Target_Crop": [
                    {
                        "name": "corn"
                    }
                ],
                "Target_Disease_Pest": [
                    {
                        "name": "Pythium spp."
                    }
                ]
            },
            {
                "low_rate": 0.039,
                "high_rate": 0.195,
                "units": "fl oz/100 lb seed",
                "max_product_per_acre_per_season": "0.0178 lb ai/A",
                "max_applications_per_season": "2 plantings per year",
                "REI": "4 hours",
                "PHI": "N/A",
                "application_Method": "Water-based slurry seed treatment",
                "Target_Crop": [
                    {
                        "name": "soybeans"
                    }
                ],
                "Target_Disease_Pest": [
                    {
                        "name": "Pythium spp."
                    },
                    {
                        "name": "Phytophthora spp."
                    }
                ]
            },
            {
                "low_rate": 0.05,
                "high_rate": 0.1,
                "units": "fl oz/100 lb seed",
                "max_product_per_acre_per_season": "0.0178 lb ai/A",
                "max_applications_per_season": "N/A",
                "REI": "4 hours",
                "PHI": "N/A",
                "application_Method": "Water-based slurry seed treatment",
                "Target_Crop": [
                    {
                        "name": "wheat"
                    }
                ],
                "Target_Disease_Pest": [
                    {
                        "name": "Pythium root rot"
                    }
                ]
            },
            {
                "low_rate": 0.0384,
                "high_rate": 0.384,
                "units": "fl oz/100 lb seed",
                "max_product_per_acre_per_season": "0.0178 lb ai/A",
                "max_applications_per_season": "N/A",
                "REI": "4 hours",
                "PHI": "N/A",
                "application_Method": "Water-based slurry seed treatment",
                "Target_Crop": [
                    {
                        "name": "cabbage"
                    }
                ],
                "Target_Disease_Pest": [
                    {
                        "name": "Pythium damping-off"
                    }
                ]
            },
            {
                "low_rate": 0.05,
                "high_rate": 0.2,
                "units": "fl oz/100 lb seed",
                "max_product_per_acre_per_season": "0.0178 lb ai/A",
                "max_applications_per_season": "N/A",
                "REI": "4 hours",
                "PHI": "N/A",
                "application_Method": "Water-based slurry seed treatment",
                "Target_Crop": [
                    {
                        "name": "snap beans"
                    }
                ],
                "Target_Disease_Pest": [
                    {
                        "name": "Pythium seed rot"
                    },
                    {
                        "name": "root rot"
                    },
                    {
                        "name": "seedling rot"
                    },
                    {
                        "name": "damping off"
                    }
                ]
            },
            {
                "low_rate": 0.05,
                "high_rate": 0.2,
                "units": "fl oz/100 lb seed",
                "max_product_per_acre_per_season": "0.0178 lb ai/A",
                "max_applications_per_season": "N/A",
                "REI": "4 hours",
                "PHI": "N/A",
                "application_Method": "Water-based slurry seed treatment",
                "Target_Crop": [
                    {
                        "name": "dry beans"
                    }
                ],
                "Target_Disease_Pest": [
                    {
                        "name": "Pythium seed rot"
                    },
                    {
                        "name": "root rot"
                    },
                    {
                        "name": "seedling rot"
                    },
                    {
                        "name": "damping off"
                    }
                ]
            },
            {
                "low_rate": 0.0384,
                "high_rate": 0.384,
                "units": "fl oz/100 lb seed",
                "max_product_per_acre_per_season": "0.0178 lb ai/A",
                "max_applications_per_season": "N/A",
                "REI": "4 hours",
                "PHI": "N/A",
                "application_Method": "Water-based slurry seed treatment",
                "Target_Crop": [
                    {
                        "name": "onions"
                    }
                ],
                "Target_Disease_Pest": [
                    {
                        "name": "Pythium damping-off"
                    }
                ]
            },
            {
                "low_rate": 0.0384,
                "high_rate": 0.384,
                "units": "fl oz/100 lb seed",
                "max_product_per_acre_per_season": "0.0178 lb ai/A",
                "max_applications_per_season": "N/A",
                "REI": "4 hours",
                "PHI": "N/A",
                "application_Method": "Water-based slurry seed treatment",
                "Target_Crop": [
                    {
                        "name": "tomatoes"
                    }
                ],
                "Target_Disease_Pest": [
                    {
                        "name": "Pythium damping-off"
                    }
                ]
            },
            {
                "low_rate": 0.0384,
                "high_rate": 0.384,
                "units": "fl oz/100 lb seed",
                "max_product_per_acre_per_season": "0.0178 lb ai/A",
                "max_applications_per_season": "N/A",
                "REI": "4 hours",
                "PHI": "N/A",
                "application_Method": "Water-based slurry seed treatment",
                "Target_Crop": [
                    {
                        "name": "squash"
                    }
                ],
                "Target_Disease_Pest": [
                    {
                        "name": "Pythium damping-off"
                    }
                ]
            },
            {
                "low_rate": 0.0384,
                "high_rate": 0.384,
                "units": "fl oz/100 lb seed",
                "max_product_per_acre_per_season": "0.0178 lb ai/A",
                "max_applications_per_season": "N/A",
                "REI": "4 hours",
                "PHI": "N/A",
                "application_Method": "Water-based slurry seed treatment",
                "Target_Crop": [
                    {
                        "name": "pumpkins"
                    }
                ],
                "Target_Disease_Pest": [
                    {
                        "name": "Pythium damping-off"
                    }
                ]
            }
        ]
    }
}