{
    "pesticide": {
        "PPE": "long-sleeved shirt and long pants, chemical-resistant gloves made of any waterproof material, shoes and socks.",
        "PPE_page": 2,
        "signal_word": "KEEP OUT OF REACH OF CHILDREN",
        "label_url": "",
        "epa_reg_no": "71368-114",
        "trade_Name": "SureGuard SC",
        "company_name": "NUFARM, INC.",
        "product_id": "220991",
        "product_type": "HERBICIDE",
        "long_island_use_restriction": "False",
        "formulation": "Liquid",
        "toxicity": "AQUATIC INVERTEBRATES",
        "product_use": "AQUATIC, NON-CROP, NURSERY, ORNAMENTAL, TURF",
        "Active_Ingredients": [
            {
                "name": "Flumioxazin",
                "mode_Of_Action": "HRAC 14",
                "pc_code": "129034",
                "active_ingredient_percentage": "41.4",
                "nys_active_ingredient_id": "102211"
            }
        ],
        "Safety_Information": {
            "general_Info": "Harmful if inhaled or absorbed through the skin. Causes moderate eye irritation. Avoid breathing spray mist. Avoid contact with skin, eyes or clothing.",
            "if_In_Eyes": "N/A",
            "if_Swallowed": "N/A",
            "if_On_Skin": "N/A",
            "if_Inhaled": "N/A",
            "physician_Note": "N/A",
            "page": 2
        },
        "Application_Info": []
    }
}