{
    "pesticide": {
        "PPE": "Applicators and other handlers must wear: long-sleeved shirt and long pants, chemical-resistant gloves, such as barrier laminate, butyl rubber > 14 mls, nitrile rubber > 14 mls, or viton > 14 mls, shoes plus socks.",
        "PPE_page": 1,
        "signal_word": "CAUTION",
        "label_url": "",
        "epa_reg_no": "34704-790",
        "trade_Name": "TRIFLURALIN 10G",
        "company_name": "LOVELAND PRODUCTS, INC.",
        "product_id": "119279",
        "product_type": "HERBICIDE",
        "long_island_use_restriction": "False",
        "formulation": "Solid",
        "toxicity": "AQUATIC INVERTEBRATES, FISH",
        "product_use": "AGRICULTURAL, NON-CROP, NURSERY, ORNAMENTAL",
        "Active_Ingredients": [
            {
                "name": "Trifluralin",
                "mode_Of_Action": "HRAC 3",
                "pc_code": "36101",
                "active_ingredient_percentage": "10.0",
                "nys_active_ingredient_id": "90262"
            }
        ],
        "Safety_Information": {
            "general_Info": "Causes eye irritation. Harmful if swallowed, inhaled or absorbed through the skin. Avoid breathing dust and contact with skin, eyes or clothing. This product may cause skin sensitization reactions in some people.",
            "if_In_Eyes": "Hold eye open and rinse slowly and gently with water for 15-20 minutes. Remove contact lenses, if present, after the first 5 minutes, then continue rinsing eye. Call a poison control center or doctor for treatment advice.",
            "if_Swallowed": "Call a poison control center or doctor immediately for treatment advice. Have a person sip a glass of water if able to swallow. Do not induce vomiting unless told to do so by the poison control center or doctor. Do not give anything by mouth to an unconscious person.",
            "if_Inhaled": "Move person to fresh air. If person is not breathing, call 911 or an ambulance, then give artificial respiration, preferably by mouth-to-mouth, if possible. Call a poison control center or doctor for further treatment advice.",
            "if_On_Skin": "Take off contaminated clothing. Rinse skin immediately with plenty of water for 15-20 minutes. Call a poison control center or doctor for treatment advice.",
            "physician_Note": "FOR A MEDICAL EMERGENCY INVOLVING THIS PRODUCT CALL: 1-866-944-8565. Have the product container or label with you when calling a poison control center or doctor, or going for treatment.",
            "page": 1
        },
        "Application_Info": [
            {
                "low_rate": 20,
                "low_rate_page": 13,
                "high_rate": 20,
                "units": "LB/A",
                "max_product_per_acre_per_season": "20 lbs",
                "max_product_per_acre_per_season_page": 13,
                "max_applications_per_season": "N/A",
                "REI": "12 hours",
                "REI_page": 5,
                "PHI": "21 days",
                "PHI_page": 13,
                "application_Method": "ground or aerial",
                "Target_Crop": [
                    {
                        "name": "alfalfa",
                        "page": 13
                    }
                ],
                "Target_Disease_Pest": [
                    {
                        "name": "barnyardgrass",
                        "page": 13
                    },
                    {
                        "name": "bromegrass",
                        "page": 13
                    },
                    {
                        "name": "cheatgrass",
                        "page": 13
                    },
                    {
                        "name": "downy brome",
                        "page": 13
                    },
                    {
                        "name": "canarygrass",
                        "page": 13
                    },
                    {
                        "name": "cheat",
                        "page": 13
                    },
                    {
                        "name": "crabgrass",
                        "page": 13
                    },
                    {
                        "name": "woolly cupgrass",
                        "page": 13
                    },
                    {
                        "name": "foxtail",
                        "page": 13
                    },
                    {
                        "name": "junglerice",
                        "page": 13
                    },
                    {
                        "name": "sandbur",
                        "page": 13
                    },
                    {
                        "name": "wild barley",
                        "page": 13
                    }
                ]
            },
            {
                "low_rate": 5,
                "low_rate_page": 15,
                "high_rate": 7.5,
                "units": "LB/A",
                "max_product_per_acre_per_season": "N/A",
                "max_product_per_acre_per_season_page": null,
                "max_applications_per_season": "N/A",
                "REI": "12 hours",
                "REI_page": 5,
                "PHI": "N/A",
                "PHI_page": null,
                "application_Method": "apply and incorporate before planting",
                "Target_Crop": [
                    {
                        "name": "snap beans",
                        "page": 15
                    }
                ],
                "Target_Disease_Pest": [
                    {
                        "name": "Annual grasses",
                        "page": 15
                    },
                    {
                        "name": "Broadleaf weeds",
                        "page": 15
                    }
                ]
            },
            {
                "low_rate": 5,
                "low_rate_page": 17,
                "high_rate": 10,
                "units": "LB/A",
                "max_product_per_acre_per_season": "N/A",
                "max_product_per_acre_per_season_page": null,
                "max_applications_per_season": "N/A",
                "REI": "12 hours",
                "REI_page": 5,
                "PHI": "N/A",
                "PHI_page": null,
                "application_Method": "apply and incorporate",
                "Target_Crop": [
                    {
                        "name": "potatoes",
                        "page": 16
                    }
                ],
                "Target_Disease_Pest": [
                    {
                        "name": "Annual grasses",
                        "page": 16
                    },
                    {
                        "name": "Broadleaf weeds",
                        "page": 16
                    }
                ]
            },
            {
                "low_rate": 5,
                "low_rate_page": 29,
                "high_rate": 12.5,
                "units": "LB/A",
                "max_product_per_acre_per_season": "N/A",
                "max_product_per_acre_per_season_page": null,
                "max_applications_per_season": "N/A",
                "REI": "12 hours",
                "REI_page": 5,
                "PHI": "N/A",
                "PHI_page": null,
                "application_Method": "apply and incorporate",
                "Target_Crop": [
                    {
                        "name": "soybeans",
                        "page": 29
                    }
                ],
                "Target_Disease_Pest": [
                    {
                        "name": "Annual grasses",
                        "page": 29
                    },
                    {
                        "name": "Broadleaf weeds",
                        "page": 29
                    }
                ]
            },
            {
                "low_rate": 3.75,
                "low_rate_page": 19,
                "high_rate": 10,
                "units": "LB/A",
                "max_product_per_acre_per_season": "N/A",
                "max_product_per_acre_per_season_page": null,
                "max_applications_per_season": "N/A",
                "REI": "12 hours",
                "REI_page": 5,
                "PHI": "N/A",
                "PHI_page": null,
                "application_Method": "postemergence broadcast",
                "Target_Crop": [
                    {
                        "name": "corn",
                        "page": 19
                    }
                ],
                "Target_Disease_Pest": [
                    {
                        "name": "Annual grasses",
                        "page": 19
                    },
                    {
                        "name": "Broadleaf weeds",
                        "page": 19
                    }
                ]
            },
            {
                "low_rate": 5,
                "low_rate_page": 26,
                "high_rate": 7.5,
                "units": "LB/A",
                "max_product_per_acre_per_season": "N/A",
                "max_product_per_acre_per_season_page": null,
                "max_applications_per_season": "N/A",
                "REI": "12 hours",
                "REI_page": 5,
                "PHI": "N/A",
                "PHI_page": null,
                "application_Method": "preplant incorporated",
                "Target_Crop": [
                    {
                        "name": "wheat",
                        "page": 26
                    }
                ],
                "Target_Disease_Pest": [
                    {
                        "name": "Annual grasses",
                        "page": 26
                    },
                    {
                        "name": "Broadleaf weeds",
                        "page": 26
                    }
                ]
            },
            {
                "low_rate": 5,
                "low_rate_page": 31,
                "high_rate": 10,
                "units": "LB/A",
                "max_product_per_acre_per_season": "N/A",
                "max_product_per_acre_per_season_page": null,
                "max_applications_per_season": "N/A",
                "REI": "12 hours",
                "REI_page": 5,
                "PHI": "N/A",
                "PHI_page": null,
                "application_Method": "apply and incorporate",
                "Target_Crop": [
                    {
                        "name": "tomatoes",
                        "page": 31
                    }
                ],
                "Target_Disease_Pest": [
                    {
                        "name": "Annual grasses",
                        "page": 31
                    },
                    {
                        "name": "Broadleaf weeds",
                        "page": 31
                    }
                ]
            },
            {
                "low_rate": 5,
                "low_rate_page": 18,
                "high_rate": 10,
                "units": "LB/A",
                "max_product_per_acre_per_season": "N/A",
                "max_product_per_acre_per_season_page": null,
                "max_applications_per_season": "N/A",
                "REI": "12 hours",
                "REI_page": 5,
                "PHI": "N/A",
                "PHI_page": null,
                "application_Method": "apply and incorporate before transplanting",
                "Target_Crop": [
                    {
                        "name": "cabbage",
                        "page": 18
                    }
                ],
                "Target_Disease_Pest": [
                    {
                        "name": "Annual grasses",
                        "page": 18
                    },
                    {
                        "name": "Broadleaf weeds",
                        "page": 18
                    }
                ]
            },
            {
                "low_rate": 10,
                "low_rate_page": 32,
                "high_rate": 20,
                "units": "LB/A",
                "max_product_per_acre_per_season": "N/A",
                "max_product_per_acre_per_season_page": null,
                "max_applications_per_season": "N/A",
                "REI": "12 hours",
                "REI_page": 5,
                "PHI": "60 days",
                "PHI_page": 32,
                "application_Method": "apply and incorporate",
                "Target_Crop": [
                    {
                        "name": "grapes",
                        "page": 32
                    }
                ],
                "Target_Disease_Pest": [
                    {
                        "name": "Annual grasses",
                        "page": 32
                    },
                    {
                        "name": "Broadleaf weeds",
                        "page": 32
                    }
                ]
            }
        ]
    }
}